EVECelery/EVECeleryBeatScheduler.py
EVECelery/EVECeleryWorker.py
EVECelery/__init__.py
EVECelery/__main__.py
EVECelery/__version__.py
EVECelery/clients/BaseClient.py
EVECelery/clients/ClientRabbitMQ.py
EVECelery/clients/ClientRedis.py
EVECelery/clients/__init__.py
EVECelery/exceptions/__init__.py
EVECelery/exceptions/tasks.py
EVECelery/exceptions/utils.py
EVECelery/tasks/TaskDirectory.py
EVECelery/tasks/__init__.py
EVECelery/tasks/BaseTasks/TaskBase.py
EVECelery/tasks/BaseTasks/TaskCached.py
EVECelery/tasks/BaseTasks/TaskESI.py
EVECelery/tasks/BaseTasks/__init__.py
EVECelery/tasks/BaseTasks/Models/ModelsBase.py
EVECelery/tasks/BaseTasks/Models/ModelsCached.py
EVECelery/tasks/BaseTasks/Models/__init__.py
EVECelery/tasks/ESI/TaskDirectory.py
EVECelery/tasks/ESI/__init__.py
EVECelery/tasks/ESI/Alliance/TaskDirectory.py
EVECelery/tasks/ESI/Alliance/__init__.py
EVECelery/tasks/ESI/Alliance/get_alliances.py
EVECelery/tasks/ESI/Alliance/get_alliances_alliance_id.py
EVECelery/tasks/ESI/Alliance/get_alliances_alliance_id_corporations.py
EVECelery/tasks/ESI/Alliance/get_alliances_alliance_id_icons.py
EVECelery/tasks/ESI/Alliance/Models/__init__.py
EVECelery/tasks/ESI/Alliance/Models/get_alliances_200.py
EVECelery/tasks/ESI/Alliance/Models/get_alliances_alliance_id_200.py
EVECelery/tasks/ESI/Alliance/Models/get_alliances_alliance_id_corporations_200.py
EVECelery/tasks/ESI/Alliance/Models/get_alliances_alliance_id_icons_200.py
EVECelery/tasks/ESI/Assets/TaskDirectory.py
EVECelery/tasks/ESI/Assets/__init__.py
EVECelery/tasks/ESI/Assets/get_characters_character_id_assets.py
EVECelery/tasks/ESI/Assets/get_corporations_corporation_id_assets.py
EVECelery/tasks/ESI/Assets/post_characters_character_id_assets_locations.py
EVECelery/tasks/ESI/Assets/post_characters_character_id_assets_names.py
EVECelery/tasks/ESI/Assets/post_corporations_corporation_id_assets_locations.py
EVECelery/tasks/ESI/Assets/post_corporations_corporation_id_assets_names.py
EVECelery-0.20.dist-info/LICENSE
EVECelery-0.20.dist-info/METADATA
EVECelery-0.20.dist-info/WHEEL
EVECelery-0.20.dist-info/entry_points.txt
EVECelery-0.20.dist-info/top_level.txt
EVECelery-0.20.dist-info/RECORD
