Metadata-Version: 2.1
Name: EVECelery
Version: 0.20
Summary: Task queue framework for building tools that interact with the EVE Online ESI API using Celery, RabbitMQ, and Redis.
Home-page: https://github.com/NullsecSpace/EVECelery
Author-email: maintainers@nullsec.space
License: MIT License
Project-URL: Documentation, https://EVECelery.nullsec.space
Project-URL: Source, https://github.com/NullsecSpace/EVECelery
Project-URL: Tracker, https://github.com/NullsecSpace/EVECelery/issues
Keywords: eve online rabbitmq esi redis message queue broker
Classifier: Development Status :: 2 - Pre-Alpha
Classifier: Programming Language :: Python :: 3.10
Classifier: Topic :: Games/Entertainment
Classifier: License :: OSI Approved :: MIT License
Requires-Python: >=3.7
License-File: LICENSE
Requires-Dist: Celery (~=5.2)
Requires-Dist: pika (~=1.3)
Requires-Dist: python-dateutil (~=2.8.2)
Requires-Dist: redis (~=4.1)
Requires-Dist: requests (~=2.27)
Requires-Dist: pydantic (~=1.10)
